semic/__init__.py
semic/code_insee.csv
semic/historique_meteo.csv
semic/semic.py
semic/gps_info/__init__.py
semic/gps_info/elevation.py
semic/gps_info/geoloc.py
semic/maps/__init__.py
semic/maps/maps.py
semic/meteo/__init__.py
semic/meteo/historiquemeteo.py
semic/meteo/meteofrance.py
semic/sentinelProcess/__init__.py
semic/sentinelProcess/sentinelAccess.py
semic/sentinelProcess/sentinelProcess.py
semic/utils/__init__.py
semic/utils/constants.py
semic/utils/utils.py
semic-0.0.5.dist-info/LICENSE
semic-0.0.5.dist-info/METADATA
semic-0.0.5.dist-info/WHEEL
semic-0.0.5.dist-info/top_level.txt
semic-0.0.5.dist-info/RECORD
