Metadata-Version: 2.1
Name: semic
Version: 0.0.5
Summary: Satellite, environmental and meteorologic information collect
Home-page: https://github.com/JasonDrt/semic
Author: JasonDrt, LesavoureyMael
Author-email: lesavoureym@gmail.com, jason.daurat@laposte.net
License: UNKNOWN
Platform: UNKNOWN
Classifier: Programming Language :: Python :: 3
Classifier: License :: OSI Approved :: GNU General Public License v3 (GPLv3)
Classifier: Operating System :: OS Independent
Requires-Dist: requests
Requires-Dist: geopy
Requires-Dist: staticmap
Requires-Dist: bs4
Requires-Dist: pandas
Requires-Dist: haversine
Requires-Dist: datetime
Requires-Dist: sentinelsat
Requires-Dist: pyproj
Requires-Dist: Pillow
